uv_lgh_test_package1/__init__.py
uv_lgh_test_package1/main.py
uv_lgh_test_package1-0.2.0.dist-info/METADATA
uv_lgh_test_package1-0.2.0.dist-info/WHEEL
uv_lgh_test_package1-0.2.0.dist-info/entry_points.txt
uv_lgh_test_package1-0.2.0.dist-info/RECORD
